README.md
setup.py
imageai/__init__.py
imageai/Classification/__init__.py
imageai/Classification/Custom/__init__.py
imageai/Detection/__init__.py
imageai/Detection/Custom/__init__.py
imageai/Detection/Custom/callbacks.py
imageai/Detection/Custom/evaluate.py
imageai/Detection/Custom/gen_anchors.py
imageai/Detection/Custom/generator.py
imageai/Detection/Custom/voc.py
imageai/Detection/Custom/utils/__init__.py
imageai/Detection/Custom/utils/bbox.py
imageai/Detection/Custom/utils/colors.py
imageai/Detection/Custom/utils/image.py
imageai/Detection/Custom/utils/multi_gpu_model.py
imageai/Detection/Custom/utils/utils.py
imageai/Detection/YOLO/__init__.py
imageai/Detection/YOLO/utils.py
imageai/Detection/YOLO/yolov3.py
imageai/Detection/keras_retinanet/__init__.py
imageai/Detection/keras_retinanet/initializers.py
imageai/Detection/keras_retinanet/losses.py
imageai/Detection/keras_retinanet/backend/__init__.py
imageai/Detection/keras_retinanet/backend/backend.py
imageai/Detection/keras_retinanet/bin/__init__.py
imageai/Detection/keras_retinanet/bin/convert_model.py
imageai/Detection/keras_retinanet/bin/debug.py
imageai/Detection/keras_retinanet/bin/evaluate.py
imageai/Detection/keras_retinanet/bin/train.py
imageai/Detection/keras_retinanet/callbacks/__init__.py
imageai/Detection/keras_retinanet/callbacks/coco.py
imageai/Detection/keras_retinanet/callbacks/common.py
imageai/Detection/keras_retinanet/callbacks/eval.py
imageai/Detection/keras_retinanet/layers/__init__.py
imageai/Detection/keras_retinanet/layers/_misc.py
imageai/Detection/keras_retinanet/layers/filter_detections.py
imageai/Detection/keras_retinanet/models/__init__.py
imageai/Detection/keras_retinanet/models/densenet.py
imageai/Detection/keras_retinanet/models/effnet.py
imageai/Detection/keras_retinanet/models/mobilenet.py
imageai/Detection/keras_retinanet/models/resnet.py
imageai/Detection/keras_retinanet/models/retinanet.py
imageai/Detection/keras_retinanet/models/senet.py
imageai_org.egg-info/PKG-INFO
imageai_org.egg-info/SOURCES.txt
imageai_org.egg-info/dependency_links.txt
imageai_org.egg-info/not-zip-safe
imageai_org.egg-info/requires.txt
imageai_org.egg-info/top_level.txt
